dscan_api_client/__init__.py
dscan_api_client/client.py
dscan_api_client/errors.py
dscan_api_client/py.typed
dscan_api_client/types.py
dscan_api_client/api/__init__.py
dscan_api_client/api/domains/__init__.py
dscan_api_client/api/domains/domains_blocked_create.py
dscan_api_client/api/domains/domains_create.py
dscan_api_client/api/domains/domains_destroy.py
dscan_api_client/api/domains/domains_list.py
dscan_api_client/api/domains/domains_partial_update.py
dscan_api_client/api/domains/domains_retrieve.py
dscan_api_client/api/domains/domains_update.py
dscan_api_client/api/programs/__init__.py
dscan_api_client/api/programs/programs_create.py
dscan_api_client/api/programs/programs_destroy.py
dscan_api_client/api/programs/programs_list.py
dscan_api_client/api/programs/programs_partial_update.py
dscan_api_client/api/programs/programs_retrieve.py
dscan_api_client/api/programs/programs_search_list.py
dscan_api_client/api/programs/programs_subdomain_check_create.py
dscan_api_client/api/programs/programs_subdomain_get_list.py
dscan_api_client/api/programs/programs_update.py
dscan_api_client/api/scans/__init__.py
dscan_api_client/api/scans/scans_create.py
dscan_api_client/api/scans/scans_destroy.py
dscan_api_client/api/scans/scans_issue_inc_create.py
dscan_api_client/api/scans/scans_list.py
dscan_api_client/api/scans/scans_partial_update.py
dscan_api_client/api/scans/scans_retrieve.py
dscan_api_client/api/scans/scans_search_by_name_list.py
dscan_api_client/api/scans/scans_search_by_program_list.py
dscan_api_client/api/scans/scans_update.py
dscan_api_client/api/scans/scans_with_status_list.py
dscan_api_client/api/settings/__init__.py
dscan_api_client/api/settings/settings_create.py
dscan_api_client/api/settings/settings_destroy.py
dscan_api_client/api/settings/settings_list.py
dscan_api_client/api/settings/settings_partial_update.py
dscan_api_client/api/settings/settings_retrieve.py
dscan_api_client/api/settings/settings_search_list.py
dscan_api_client-2.2.10.dist-info/LICENSE
dscan_api_client-2.2.10.dist-info/METADATA
dscan_api_client-2.2.10.dist-info/WHEEL
dscan_api_client-2.2.10.dist-info/top_level.txt
dscan_api_client-2.2.10.dist-info/RECORD
