Metadata-Version: 2.1
Name: dscan-api-client
Version: 2.2.10
Summary: A client library for accessing Dscan API
Requires-Python: >=3.8, <4
License-File: LICENSE
Requires-Dist: httpx <0.25.0,>=0.15.0
Requires-Dist: attrs >=21.3.0
Requires-Dist: python-dateutil <3,>=2.8.0
